fosfairy/__init__.py
fosfairy/pl/__init__.py
fosfairy/pl/basic.py
fosfairy/pp/__init__.py
fosfairy/pp/basic.py
fosfairy/tl/__init__.py
fosfairy/tl/basic.py
fosfairy-0.0.6.dist-info/METADATA
fosfairy-0.0.6.dist-info/WHEEL
fosfairy-0.0.6.dist-info/licenses/LICENSE
fosfairy-0.0.6.dist-info/RECORD
