Metadata-Version: 2.1
Name: fosfairy
Version: 0.0.6
Summary: TFs, IEGs and more!
Project-URL: Documentation, https://fosfairy.readthedocs.io/
Project-URL: Source, https://github.com/lhqing/fosfairy
Project-URL: Home-page, https://github.com/lhqing/fosfairy
Author: Hanqing Liu
Maintainer-email: Hanqing Liu <hanqingliu@fas.harvard.edu>
License: MIT License
License-File: LICENSE
Requires-Python: >=3.9
Requires-Dist: anndata
Requires-Dist: session-info
Provides-Extra: dev
Requires-Dist: pre-commit; extra == 'dev'
Requires-Dist: twine>=4.0.2; extra == 'dev'
Provides-Extra: doc
Requires-Dist: docutils!=0.18.*,!=0.19.*,>=0.8; extra == 'doc'
Requires-Dist: ipykernel; extra == 'doc'
Requires-Dist: ipython; extra == 'doc'
Requires-Dist: myst-nb; extra == 'doc'
Requires-Dist: sphinx-autodoc-typehints; extra == 'doc'
Requires-Dist: sphinx-book-theme>=1.0.0; extra == 'doc'
Requires-Dist: sphinx-copybutton; extra == 'doc'
Requires-Dist: sphinx>=4; extra == 'doc'
Requires-Dist: sphinxcontrib-bibtex>=1.0.0; extra == 'doc'
Requires-Dist: sphinxext-opengraph; extra == 'doc'
Provides-Extra: test
Requires-Dist: pytest; extra == 'test'
Requires-Dist: pytest-cov; extra == 'test'
